datacompy/__init__.py
datacompy/_version.py
datacompy/core.py
datacompy/sparkcompare.py
datacompy/templates/column_comparison.txt
datacompy/templates/column_summary.txt
datacompy/templates/fav_column_summary.txt
datacompy/templates/header.txt
datacompy/templates/row_summary.txt
datacompy_abmn614-0.7.7.dist-info/LICENSE
datacompy_abmn614-0.7.7.dist-info/METADATA
datacompy_abmn614-0.7.7.dist-info/WHEEL
datacompy_abmn614-0.7.7.dist-info/top_level.txt
datacompy_abmn614-0.7.7.dist-info/RECORD
