Metadata-Version: 2.1
Name: datacompy-abmn614
Version: 0.7.7
Summary: Dataframe comparison in Python
Home-page: https://github.com/abmn614/datacompy.git
License: Apache-2.0
Platform: UNKNOWN
License-File: LICENSE
Requires-Dist: pandas (>=0.25.0)
Requires-Dist: numpy (>=1.11.3)
Requires-Dist: ordered-set (>=4.0.2)
Provides-Extra: build
Requires-Dist: twine ; extra == 'build'
Requires-Dist: wheel ; extra == 'build'
Provides-Extra: dev
Requires-Dist: pytest ; extra == 'dev'
Requires-Dist: pytest-cov ; extra == 'dev'
Requires-Dist: sphinx ; extra == 'dev'
Requires-Dist: sphinx-rtd-theme ; extra == 'dev'
Requires-Dist: pre-commit ; extra == 'dev'
Requires-Dist: black ; extra == 'dev'
Requires-Dist: isort ; extra == 'dev'
Requires-Dist: twine ; extra == 'dev'
Requires-Dist: wheel ; extra == 'dev'
Provides-Extra: docs
Requires-Dist: sphinx ; extra == 'docs'
Requires-Dist: sphinx-rtd-theme ; extra == 'docs'
Provides-Extra: qa
Requires-Dist: pre-commit ; extra == 'qa'
Requires-Dist: black ; extra == 'qa'
Requires-Dist: isort ; extra == 'qa'
Provides-Extra: spark
Requires-Dist: pyspark (>=2.2.0) ; extra == 'spark'
Provides-Extra: tests
Requires-Dist: pytest ; extra == 'tests'
Requires-Dist: pytest-cov ; extra == 'tests'
